cellpick/__init__.py
cellpick/__main__.py
cellpick/app/__init__.py
cellpick/app/algorithms.py
cellpick/app/components.py
cellpick/app/image_viewer.py
cellpick/app/style.py
cellpick/app/ui_components.py
cellpick/app/ui_main.py
cellpick/app/utils.py
cellpick/assets/.DS_Store
cellpick/assets/Roboto-Regular.ttf
cellpick/assets/logo-h.png
cellpick/assets/logo-h.svg
cellpick/assets/logo-small-h.svg
cellpick/assets/logo-small.svg
cellpick/assets/logo.png
cellpick/assets/logo.svg
cellpick/assets/logo_small.png
cellpick-0.1.4.dist-info/METADATA
cellpick-0.1.4.dist-info/WHEEL
cellpick-0.1.4.dist-info/entry_points.txt
cellpick-0.1.4.dist-info/RECORD
