Metadata-Version: 2.1
Name: cellpick
Version: 0.1.4
Summary: An interactive cell selection tool for spatial omics
License: BSD3
Author: Lucas Miranda, Paolo Pellizzoni
Requires-Python: >=3.9,<3.14
Classifier: License :: Other/Proprietary License
Classifier: Programming Language :: Python :: 3
Classifier: Programming Language :: Python :: 3.9
Classifier: Programming Language :: Python :: 3.10
Classifier: Programming Language :: Python :: 3.11
Classifier: Programming Language :: Python :: 3.12
Requires-Dist: czifile (>=2019.7.2.1,<2020.0.0.0)
Requires-Dist: imagecodecs (==2024.12.30)
Requires-Dist: lxml (>=5.4.0,<6.0.0)
Requires-Dist: numpy (>=2.0.2)
Requires-Dist: pandas (>=2.3.0,<3.0.0)
Requires-Dist: pyobjc (>=11.1,<12.0) ; sys_platform == "darwin"
Requires-Dist: pyside6 (>=6.9.1,<7.0.0)
Requires-Dist: qt-material (>=2.17,<3.0)
Requires-Dist: scikit-image (>=0.24.0)
Requires-Dist: shapely (>=2.0.7)
Requires-Dist: tifffile (==2024.8.30)
Requires-Dist: tqdm (>=4.67.1,<5.0.0)
Requires-Dist: untangle (>=1.2.1,<2.0.0)
